directmessages/__init__.py
directmessages/admin.py
directmessages/apps.py
directmessages/migrations/0001_initial.py
directmessages/migrations/__init__.py
directmessages/models.py
directmessages/serializers.py
directmessages/services.py
directmessages/signals.py
directmessages/urls.py
directmessages/views.py
drf_directmessages-0.0.1.dist-info/METADATA
drf_directmessages-0.0.1.dist-info/WHEEL
drf_directmessages-0.0.1.dist-info/RECORD
