Metadata-Version: 2.1
Name: drf-directmessages
Version: 0.0.1
Summary: An API allowing users to directly message each other.
Author: Garreth Cain
Author-email: garrethccain@gmail.com
Requires-Python: >=3.9,<4.0
Classifier: Programming Language :: Python :: 3
Classifier: Programming Language :: Python :: 3.9
Classifier: Programming Language :: Python :: 3.10
Classifier: Programming Language :: Python :: 3.11
Requires-Dist: django (>=4.2.1,<5.0.0)
Requires-Dist: djangorestframework (>=3.14.0,<4.0.0)
